{"version":1,"resource":"file:///home/ben/code/c/test/temperature_conversion/while_loop.c","entries":[{"id":"pnVV.c","timestamp":1740751442495},{"id":"rSfO.c","timestamp":1740751484985},{"id":"6sBz.c","timestamp":1740751502955},{"id":"j8Z5.c","timestamp":1740751560155},{"id":"6668.c","timestamp":1740751594100},{"id":"1Yps.c","timestamp":1740751682389},{"id":"nCQ3.c","timestamp":1740751716223},{"id":"VHBV.c","timestamp":1740752789262},{"id":"qDJx.c","timestamp":1740752803519},{"id":"MiVN.c","timestamp":1740752855310},{"id":"flqi.c","timestamp":1740752969879},{"id":"lf9x.c","timestamp":1740753007782},{"id":"jIca.c","timestamp":1740753022524},{"id":"11GY.c","timestamp":1740753050030},{"id":"dLpJ.c","timestamp":1740753062985},{"id":"8TES.c","timestamp":1740753560043},{"id":"wte8.c","timestamp":1740753602264},{"id":"ivuo.c","timestamp":1740837335532},{"id":"CoZq.c","source":"moved.source","sourceDescription":"~/code/c/test/main.c","timestamp":1740839387935},{"id":"X2C5.c","source":"renamed.source","sourceDescription":"~/code/c/test/temperature_conversion/main.c","timestamp":1740839421645},{"id":"aQe6.c","source":"renamed.source","sourceDescription":"~/code/c/test/temperature_conversion/While_loop.c","timestamp":1740839439583}]}